setup.cfg
setup.py
json_to_sqlite/__init__.py
json_to_sqlite/__main__.py
json_to_sqlite/main.py
json_to_sqlite.egg-info/PKG-INFO
json_to_sqlite.egg-info/SOURCES.txt
json_to_sqlite.egg-info/dependency_links.txt
json_to_sqlite.egg-info/entry_points.txt
json_to_sqlite.egg-info/requires.txt
json_to_sqlite.egg-info/top_level.txt