Metadata-Version: 1.1
Name: json-to-sqlite
Version: 0.13
Summary: convert to json to column based sqlite
Home-page: https://github.com/jeremiahsavage/json-to-sqlite
Author: Jeremiah H. Savage
Author-email: jeremiahsavage@gmail.com
License: Apache 2.0
Platform: UNKNOWN
Classifier: Development Status :: 3 - Alpha
Classifier: Intended Audience :: Developers
Classifier: License :: OSI Approved :: Apache Software License
Classifier: Programming Language :: Python
Classifier: Programming Language :: Python :: 3
